setup.cfg
setup.py
hello_crazy_people/__init__.py
hello_crazy_people/hello_crazy_people.py
hello_crazy_people.egg-info/PKG-INFO
hello_crazy_people.egg-info/SOURCES.txt
hello_crazy_people.egg-info/dependency_links.txt
hello_crazy_people.egg-info/not-zip-safe
hello_crazy_people.egg-info/top_level.txt