Metadata-Version: 1.0
Name: hello-crazy-people
Version: 0.0
Summary: Радостное приветствие.
Home-page: UNKNOWN
Author: UNKNOWN
Author-email: tsyganlee@gmail.com
License: UNKNOWN
Platform: UNKNOWN
